pynterfacelib/__init__.py
pynterfacelib-1.0.1.dist-info/METADATA
pynterfacelib-1.0.1.dist-info/WHEEL
pynterfacelib-1.0.1.dist-info/top_level.txt
pynterfacelib-1.0.1.dist-info/RECORD
