Metadata-Version: 2.1
Name: pynterfacelib
Version: 1.0.1
Summary: Library for checking interface compliance in Python
Home-page: https://github.com/bekha-io/pynterface
Author: Bekhruz Iskandarzoda
Author-email: iskandarzoda@outlook.com
License: MIT
Keywords: interface checker development
Platform: UNKNOWN
Classifier: Development Status :: 5 - Production/Stable
Classifier: Intended Audience :: Developers
Classifier: License :: OSI Approved :: MIT License
Classifier: Programming Language :: Python :: 3
Classifier: Programming Language :: Python :: 3.6
Classifier: Programming Language :: Python :: 3.7
Classifier: Programming Language :: Python :: 3.8
Classifier: Programming Language :: Python :: 3.9
Requires-Python: >=3.6
